microbeseq_cc_training_example/__init__.py
microbeseq_cc_training_example/_modidx.py
microbeseq_cc_training_example/blast_example.py
microbeseq_cc_training_example/core.py
microbeseq_cc_training_example-0.0.1.dist-info/LICENSE
microbeseq_cc_training_example-0.0.1.dist-info/METADATA
microbeseq_cc_training_example-0.0.1.dist-info/WHEEL
microbeseq_cc_training_example-0.0.1.dist-info/entry_points.txt
microbeseq_cc_training_example-0.0.1.dist-info/top_level.txt
microbeseq_cc_training_example-0.0.1.dist-info/RECORD
