Metadata-Version: 2.1
Name: microbeseq_cc_training_example
Version: 0.0.1
Summary: microbeseq training
Home-page: https://github.com/ssi-dk/microbeseq_cc_training_example
Author: githubz0r
Author-email: lebc@ssi.dk
License: Apache Software License 2.0
Keywords: nbdev jupyter notebook python
Classifier: Development Status :: 4 - Beta
Classifier: Intended Audience :: Developers
Classifier: Natural Language :: English
Classifier: Programming Language :: Python :: 3.7
Classifier: Programming Language :: Python :: 3.8
Classifier: Programming Language :: Python :: 3.9
Classifier: Programming Language :: Python :: 3.10
Classifier: License :: OSI Approved :: Apache Software License
Requires-Python: >=3.7
License-File: LICENSE
Requires-Dist: fastcore
Requires-Dist: python-dotenv
Requires-Dist: envyaml
Requires-Dist: pandas
Requires-Dist: matplotlib
Requires-Dist: sqlite
Provides-Extra: dev
